{"city": "taranto", "updated_at": "2022-09-25T23:00:00+02:00", "coalitions": {"cdx": "Fratelli d'Italia + Lega + Forza Italia + Noi Moderati", "csxm5s": "Partito Democratico + Alleanza Verdi e Sinistra + +Europa + Impegno Civico + Azione/Italia Viva + Movimento 5 Stelle"}, "sections": [{"section": 1, "politiche2022": {"cdx_votes": 141.0, "cdx_pct": 40.285714285714285, "csxm5s_votes": 199.0, "csxm5s_pct": 56.85714285714286, "total_votes": 350.0, "turnout": 50.35971223021583}}, {"section": 2, "politiche2022": {"cdx_votes": 151.0, "cdx_pct": 42.53521126760563, "csxm5s_votes": 190.0, "csxm5s_pct": 53.52112676056338, "total_votes": 355.0, "turnout": 45.28061224489796}}, {"section": 3, "politiche2022": {"cdx_votes": 137.0, "cdx_pct": 41.389728096676734, "csxm5s_votes": 179.0, "csxm5s_pct": 54.0785498489426, "total_votes": 331.0, "turnout": 46.55414908579465}}, {"section": 4, "politiche2022": {"cdx_votes": 151.0, "cdx_pct": 33.48115299334812, "csxm5s_votes": 283.0, "csxm5s_pct": 62.74944567627494, "total_votes": 451.0, "turnout": 54.8661800486618}}, {"section": 5, "politiche2022": {"cdx_votes": 179.0, "cdx_pct": 36.68032786885246, "csxm5s_votes": 297.0, "csxm5s_pct": 60.86065573770492, "total_votes": 488.0, "turnout": 50.25746652935118}}, {"section": 6, "politiche2022": {"cdx_votes": 153.0, "cdx_pct": 34.93150684931507, "csxm5s_votes": 265.0, "csxm5s_pct": 60.50228310502283, "total_votes": 438.0, "turnout": 49.65986394557823}}, {"section": 7, "politiche2022": {"cdx_votes": 161.0, "cdx_pct": 41.70984455958549, "csxm5s_votes": 216.0, "csxm5s_pct": 55.95854922279793, "total_votes": 386.0, "turnout": 48.18976279650437}}, {"section": 8, "politiche2022": {"cdx_votes": 214.0, "cdx_pct": 38.35125448028674, "csxm5s_votes": 326.0, "csxm5s_pct": 58.422939068100355, "total_votes": 558.0, "turnout": 52.69121813031161}}, {"section": 9, "politiche2022": {"cdx_votes": 179.0, "cdx_pct": 33.90151515151515, "csxm5s_votes": 331.0, "csxm5s_pct": 62.689393939393945, "total_votes": 528.0, "turnout": 54.43298969072165}}, {"section": 10, "politiche2022": {"cdx_votes": 213.0, "cdx_pct": 38.86861313868613, "csxm5s_votes": 317.0, "csxm5s_pct": 57.846715328467155, "total_votes": 548.0, "turnout": 51.79584120982986}}, {"section": 11, "politiche2022": {"cdx_votes": 215.0, "cdx_pct": 40.48964218455744, "csxm5s_votes": 299.0, "csxm5s_pct": 56.30885122410546, "total_votes": 531.0, "turnout": 51.106833493743984}}, {"section": 12, "politiche2022": {"cdx_votes": 212.0, "cdx_pct": 42.91497975708502, "csxm5s_votes": 269.0, "csxm5s_pct": 54.453441295546554, "total_votes": 494.0, "turnout": 50.050658561296856}}, {"section": 13, "politiche2022": {"cdx_votes": 206.0, "cdx_pct": 30.428360413589367, "csxm5s_votes": 461.0, "csxm5s_pct": 68.09453471196456, "total_votes": 677.0, "turnout": 53.01487862176977}}, {"section": 14, "politiche2022": {"cdx_votes": 187.0, "cdx_pct": 35.551330798479086, "csxm5s_votes": 316.0, "csxm5s_pct": 60.07604562737643, "total_votes": 526.0, "turnout": 53.07769929364279}}, {"section": 15, "politiche2022": {"cdx_votes": 154.0, "cdx_pct": 36.32075471698113, "csxm5s_votes": 257.0, "csxm5s_pct": 60.613207547169814, "total_votes": 424.0, "turnout": 54.85122897800776}}, {"section": 16, "politiche2022": {"cdx_votes": 142.0, "cdx_pct": 35.768261964735515, "csxm5s_votes": 247.0, "csxm5s_pct": 62.21662468513854, "total_votes": 397.0, "turnout": 44.65691788526434}}, {"section": 17, "politiche2022": {"cdx_votes": 218.0, "cdx_pct": 40.147329650092075, "csxm5s_votes": 317.0, "csxm5s_pct": 58.3793738489871, "total_votes": 543.0, "turnout": 50.0}}, {"section": 18, "politiche2022": {"cdx_votes": 180.0, "cdx_pct": 48.257372654155496, "csxm5s_votes": 183.0, "csxm5s_pct": 49.06166219839142, "total_votes": 373.0, "turnout": 44.08983451536643}}, {"section": 19, "politiche2022": {"cdx_votes": 237.0, "cdx_pct": 43.970315398886825, "csxm5s_votes": 284.0, "csxm5s_pct": 52.69016697588126, "total_votes": 539.0, "turnout": 57.46268656716418}}, {"section": 20, "politiche2022": {"cdx_votes": 237.0, "cdx_pct": 38.72549019607843, "csxm5s_votes": 351.0, "csxm5s_pct": 57.35294117647059, "total_votes": 612.0, "turnout": 53.92070484581498}}, {"section": 21, "politiche2022": {"cdx_votes": 172.0, "cdx_pct": 36.440677966101696, "csxm5s_votes": 277.0, "csxm5s_pct": 58.686440677966104, "total_votes": 472.0, "turnout": 55.529411764705884}}, {"section": 22, "politiche2022": {"cdx_votes": 167.0, "cdx_pct": 40.731707317073166, "csxm5s_votes": 223.0, "csxm5s_pct": 54.390243902439025, "total_votes": 410.0, "turnout": 52.903225806451616}}, {"section": 23, "politiche2022": {"cdx_votes": 227.0, "cdx_pct": 35.80441640378549, "csxm5s_votes": 368.0, "csxm5s_pct": 58.0441640378549, "total_votes": 634.0, "turnout": 56.405693950177934}}, {"section": 24, "politiche2022": {"cdx_votes": 296.0, "cdx_pct": 42.46771879483501, "csxm5s_votes": 374.0, "csxm5s_pct": 53.65853658536586, "total_votes": 697.0, "turnout": 57.41350906095551}}, {"section": 25, "politiche2022": {"cdx_votes": 297.0, "cdx_pct": 43.42105263157895, "csxm5s_votes": 353.0, "csxm5s_pct": 51.60818713450293, "total_votes": 684.0, "turnout": 58.41161400512382}}, {"section": 26, "politiche2022": {"cdx_votes": 282.0, "cdx_pct": 42.922374429223744, "csxm5s_votes": 351.0, "csxm5s_pct": 53.42465753424658, "total_votes": 657.0, "turnout": 59.457013574660635}}, {"section": 27, "politiche2022": {"cdx_votes": 281.0, "cdx_pct": 39.082058414464534, "csxm5s_votes": 412.0, "csxm5s_pct": 57.301808066759385, "total_votes": 719.0, "turnout": 57.70465489566613}}, {"section": 28, "politiche2022": {"cdx_votes": 244.0, "cdx_pct": 35.82966226138032, "csxm5s_votes": 403.0, "csxm5s_pct": 59.1776798825257, "total_votes": 681.0, "turnout": 57.275021026072324}}, {"section": 29, "politiche2022": {"cdx_votes": 236.0, "cdx_pct": 40.97222222222222, "csxm5s_votes": 318.0, "csxm5s_pct": 55.208333333333336, "total_votes": 576.0, "turnout": 59.320288362512876}}, {"section": 30, "politiche2022": {"cdx_votes": 252.0, "cdx_pct": 47.81783681214421, "csxm5s_votes": 259.0, "csxm5s_pct": 49.146110056926, "total_votes": 527.0, "turnout": 57.47001090512541}}, {"section": 31, "politiche2022": {"cdx_votes": 213.0, "cdx_pct": 44.28274428274428, "csxm5s_votes": 253.0, "csxm5s_pct": 52.5987525987526, "total_votes": 481.0, "turnout": 51.943844492440604}}, {"section": 32, "politiche2022": {"cdx_votes": 226.0, "cdx_pct": 43.883495145631066, "csxm5s_votes": 264.0, "csxm5s_pct": 51.262135922330096, "total_votes": 515.0, "turnout": 57.7354260089686}}, {"section": 33, "politiche2022": {"cdx_votes": 262.0, "cdx_pct": 44.7098976109215, "csxm5s_votes": 300.0, "csxm5s_pct": 51.19453924914675, "total_votes": 586.0, "turnout": 54.1089566020314}}, {"section": 34, "politiche2022": {"cdx_votes": 209.0, "cdx_pct": 35.483870967741936, "csxm5s_votes": 362.0, "csxm5s_pct": 61.460101867572156, "total_votes": 589.0, "turnout": 62.32804232804233}}, {"section": 35, "politiche2022": {"cdx_votes": 312.0, "cdx_pct": 41.6, "csxm5s_votes": 415.0, "csxm5s_pct": 55.333333333333336, "total_votes": 750.0, "turnout": 59.241706161137444}}, {"section": 36, "politiche2022": {"cdx_votes": 195.0, "cdx_pct": 32.663316582914575, "csxm5s_votes": 366.0, "csxm5s_pct": 61.30653266331658, "total_votes": 597.0, "turnout": 54.3221110100091}}, {"section": 37, "politiche2022": {"cdx_votes": 212.0, "cdx_pct": 35.21594684385382, "csxm5s_votes": 374.0, "csxm5s_pct": 62.12624584717608, "total_votes": 602.0, "turnout": 60.86956521739131}}, {"section": 38, "politiche2022": {"cdx_votes": 129.0, "cdx_pct": 31.15942028985507, "csxm5s_votes": 268.0, "csxm5s_pct": 64.73429951690821, "total_votes": 414.0, "turnout": 58.80681818181818}}, {"section": 39, "politiche2022": {"cdx_votes": 138.0, "cdx_pct": 33.82352941176471, "csxm5s_votes": 256.0, "csxm5s_pct": 62.745098039215684, "total_votes": 408.0, "turnout": 62.57668711656442}}, {"section": 40, "politiche2022": {"cdx_votes": 112.0, "cdx_pct": 31.11111111111111, "csxm5s_votes": 221.0, "csxm5s_pct": 61.38888888888889, "total_votes": 360.0, "turnout": 53.09734513274337}}, {"section": 41, "politiche2022": {"cdx_votes": 141.0, "cdx_pct": 35.25, "csxm5s_votes": 248.0, "csxm5s_pct": 62.0, "total_votes": 400.0, "turnout": 57.47126436781609}}, {"section": 42, "politiche2022": {"cdx_votes": 114.0, "cdx_pct": 30.07915567282322, "csxm5s_votes": 251.0, "csxm5s_pct": 66.2269129287599, "total_votes": 379.0, "turnout": 63.69747899159663}}, {"section": 43, "politiche2022": {"cdx_votes": 118.0, "cdx_pct": 30.412371134020617, "csxm5s_votes": 250.0, "csxm5s_pct": 64.43298969072166, "total_votes": 388.0, "turnout": 49.36386768447837}}, {"section": 44, "politiche2022": {"cdx_votes": 137.0, "cdx_pct": 32.31132075471698, "csxm5s_votes": 272.0, "csxm5s_pct": 64.15094339622641, "total_votes": 424.0, "turnout": 56.60881174899867}}, {"section": 45, "politiche2022": {"cdx_votes": 97.0, "cdx_pct": 30.5993690851735, "csxm5s_votes": 204.0, "csxm5s_pct": 64.35331230283911, "total_votes": 317.0, "turnout": 52.310231023102304}}, {"section": 46, "politiche2022": {"cdx_votes": 108.0, "cdx_pct": 27.906976744186046, "csxm5s_votes": 263.0, "csxm5s_pct": 67.95865633074936, "total_votes": 387.0, "turnout": 59.44700460829493}}, {"section": 47, "politiche2022": {"cdx_votes": 106.0, "cdx_pct": 30.28571428571429, "csxm5s_votes": 235.0, "csxm5s_pct": 67.14285714285714, "total_votes": 350.0, "turnout": 42.3728813559322}}, {"section": 48, "politiche2022": {"cdx_votes": 96.0, "cdx_pct": 30.86816720257235, "csxm5s_votes": 198.0, "csxm5s_pct": 63.665594855305464, "total_votes": 311.0, "turnout": 47.480916030534345}}, {"section": 49, "politiche2022": {"cdx_votes": 239.0, "cdx_pct": 32.73972602739726, "csxm5s_votes": 466.0, "csxm5s_pct": 63.83561643835617, "total_votes": 730.0, "turnout": 52.10563882940756}}, {"section": 50, "politiche2022": {"cdx_votes": 171.0, "cdx_pct": 30.866425992779785, "csxm5s_votes": 358.0, "csxm5s_pct": 64.62093862815884, "total_votes": 554.0, "turnout": 62.387387387387385}}, {"section": 51, "politiche2022": {"cdx_votes": 226.0, "cdx_pct": 31.608391608391607, "csxm5s_votes": 458.0, "csxm5s_pct": 64.05594405594405, "total_votes": 715.0, "turnout": 61.42611683848798}}, {"section": 52, "politiche2022": {"cdx_votes": 186.0, "cdx_pct": 33.87978142076503, "csxm5s_votes": 348.0, "csxm5s_pct": 63.387978142076506, "total_votes": 549.0, "turnout": 58.40425531914894}}, {"section": 53, "politiche2022": {"cdx_votes": 165.0, "cdx_pct": 37.93103448275862, "csxm5s_votes": 253.0, "csxm5s_pct": 58.160919540229884, "total_votes": 435.0, "turnout": 53.17848410757946}}, {"section": 54, "politiche2022": {"cdx_votes": 306.0, "cdx_pct": 39.130434782608695, "csxm5s_votes": 444.0, "csxm5s_pct": 56.77749360613811, "total_votes": 782.0, "turnout": 57.163742690058484}}, {"section": 55, "politiche2022": {"cdx_votes": 233.0, "cdx_pct": 38.25944170771757, "csxm5s_votes": 358.0, "csxm5s_pct": 58.78489326765188, "total_votes": 609.0, "turnout": 61.63967611336032}}, {"section": 56, "politiche2022": {"cdx_votes": 156.0, "cdx_pct": 30.29126213592233, "csxm5s_votes": 348.0, "csxm5s_pct": 67.57281553398057, "total_votes": 515.0, "turnout": 61.750599520383695}}, {"section": 57, "politiche2022": {"cdx_votes": 132.0, "cdx_pct": 27.27272727272727, "csxm5s_votes": 326.0, "csxm5s_pct": 67.35537190082644, "total_votes": 484.0, "turnout": 62.05128205128205}}, {"section": 58, "politiche2022": {"cdx_votes": 168.0, "cdx_pct": 32.24568138195777, "csxm5s_votes": 339.0, "csxm5s_pct": 65.06717850287907, "total_votes": 521.0, "turnout": 64.24167694204685}}, {"section": 59, "politiche2022": {"cdx_votes": 203.0, "cdx_pct": 39.80392156862745, "csxm5s_votes": 295.0, "csxm5s_pct": 57.84313725490197, "total_votes": 510.0, "turnout": 60.07067137809188}}, {"section": 60, "politiche2022": {"cdx_votes": 129.0, "cdx_pct": 33.33333333333333, "csxm5s_votes": 247.0, "csxm5s_pct": 63.82428940568475, "total_votes": 387.0, "turnout": 59.44700460829493}}, {"section": 61, "politiche2022": {"cdx_votes": 176.0, "cdx_pct": 37.8494623655914, "csxm5s_votes": 278.0, "csxm5s_pct": 59.78494623655914, "total_votes": 465.0, "turnout": 59.16030534351145}}, {"section": 62, "politiche2022": {"cdx_votes": 124.0, "cdx_pct": 35.53008595988539, "csxm5s_votes": 220.0, "csxm5s_pct": 63.03724928366762, "total_votes": 349.0, "turnout": 54.53125}}, {"section": 63, "politiche2022": {"cdx_votes": 147.0, "cdx_pct": 32.666666666666664, "csxm5s_votes": 285.0, "csxm5s_pct": 63.33333333333333, "total_votes": 450.0, "turnout": 59.13272010512484}}, {"section": 64, "politiche2022": {"cdx_votes": 140.0, "cdx_pct": 41.66666666666667, "csxm5s_votes": 193.0, "csxm5s_pct": 57.44047619047619, "total_votes": 336.0, "turnout": 47.93152639087018}}, {"section": 65, "politiche2022": {"cdx_votes": 122.0, "cdx_pct": 29.397590361445786, "csxm5s_votes": 286.0, "csxm5s_pct": 68.9156626506024, "total_votes": 415.0, "turnout": 62.594268476621416}}, {"section": 66, "politiche2022": {"cdx_votes": 122.0, "cdx_pct": 35.36231884057971, "csxm5s_votes": 212.0, "csxm5s_pct": 61.44927536231884, "total_votes": 345.0, "turnout": 53.40557275541795}}, {"section": 67, "politiche2022": {"cdx_votes": 123.0, "cdx_pct": 34.55056179775281, "csxm5s_votes": 215.0, "csxm5s_pct": 60.39325842696629, "total_votes": 356.0, "turnout": 51.14942528735632}}, {"section": 68, "politiche2022": {"cdx_votes": 207.0, "cdx_pct": 37.16337522441652, "csxm5s_votes": 329.0, "csxm5s_pct": 59.06642728904848, "total_votes": 557.0, "turnout": 57.960457856399586}}, {"section": 69, "politiche2022": {"cdx_votes": 125.0, "cdx_pct": 30.120481927710845, "csxm5s_votes": 282.0, "csxm5s_pct": 67.95180722891565, "total_votes": 415.0, "turnout": 60.14492753623188}}, {"section": 70, "politiche2022": {"cdx_votes": 192.0, "cdx_pct": 41.73913043478261, "csxm5s_votes": 254.0, "csxm5s_pct": 55.21739130434783, "total_votes": 460.0, "turnout": 51.45413870246085}}, {"section": 71, "politiche2022": {"cdx_votes": 202.0, "cdx_pct": 44.395604395604394, "csxm5s_votes": 241.0, "csxm5s_pct": 52.96703296703297, "total_votes": 455.0, "turnout": 53.341148886283705}}, {"section": 72, "politiche2022": {"cdx_votes": 109.0, "cdx_pct": 29.945054945054945, "csxm5s_votes": 242.0, "csxm5s_pct": 66.48351648351648, "total_votes": 364.0, "turnout": 49.18918918918919}}, {"section": 73, "politiche2022": {"cdx_votes": 103.0, "cdx_pct": 30.383480825958703, "csxm5s_votes": 213.0, "csxm5s_pct": 62.83185840707964, "total_votes": 339.0, "turnout": 47.67932489451477}}, {"section": 74, "politiche2022": {"cdx_votes": 124.0, "cdx_pct": 31.876606683804624, "csxm5s_votes": 250.0, "csxm5s_pct": 64.26735218508998, "total_votes": 389.0, "turnout": 51.0498687664042}}, {"section": 75, "politiche2022": {"cdx_votes": 174.0, "cdx_pct": 41.62679425837321, "csxm5s_votes": 222.0, "csxm5s_pct": 53.110047846889955, "total_votes": 418.0, "turnout": 57.81466113416322}}, {"section": 76, "politiche2022": {"cdx_votes": 131.0, "cdx_pct": 32.83208020050125, "csxm5s_votes": 253.0, "csxm5s_pct": 63.40852130325815, "total_votes": 399.0, "turnout": 54.58276333789329}}, {"section": 77, "politiche2022": {"cdx_votes": 160.0, "cdx_pct": 38.83495145631068, "csxm5s_votes": 240.0, "csxm5s_pct": 58.252427184466015, "total_votes": 412.0, "turnout": 51.75879396984925}}, {"section": 78, "politiche2022": {"cdx_votes": 106.0, "cdx_pct": 28.804347826086957, "csxm5s_votes": 253.0, "csxm5s_pct": 68.75, "total_votes": 368.0, "turnout": 50.13623978201635}}, {"section": 79, "politiche2022": {"cdx_votes": 140.0, "cdx_pct": 35.714285714285715, "csxm5s_votes": 219.0, "csxm5s_pct": 55.86734693877551, "total_votes": 392.0, "turnout": 49.62025316455696}}, {"section": 80, "politiche2022": {"cdx_votes": 122.0, "cdx_pct": 34.173669467787114, "csxm5s_votes": 218.0, "csxm5s_pct": 61.06442577030813, "total_votes": 357.0, "turnout": 48.178137651821864}}, {"section": 81, "politiche2022": {"cdx_votes": 159.0, "cdx_pct": 43.44262295081967, "csxm5s_votes": 198.0, "csxm5s_pct": 54.09836065573771, "total_votes": 366.0, "turnout": 50.69252077562327}}, {"section": 82, "politiche2022": {"cdx_votes": 90.0, "cdx_pct": 26.08695652173913, "csxm5s_votes": 250.0, "csxm5s_pct": 72.46376811594203, "total_votes": 345.0, "turnout": 51.646706586826355}}, {"section": 83, "politiche2022": {"cdx_votes": 181.0, "cdx_pct": 42.38875878220141, "csxm5s_votes": 239.0, "csxm5s_pct": 55.97189695550351, "total_votes": 427.0, "turnout": 53.98230088495575}}, {"section": 84, "politiche2022": {"cdx_votes": 200.0, "cdx_pct": 36.90036900369004, "csxm5s_votes": 327.0, "csxm5s_pct": 60.332103321033216, "total_votes": 542.0, "turnout": 55.64681724845995}}, {"section": 85, "politiche2022": {"cdx_votes": 163.0, "cdx_pct": 32.53493013972056, "csxm5s_votes": 322.0, "csxm5s_pct": 64.27145708582835, "total_votes": 501.0, "turnout": 52.73684210526316}}, {"section": 86, "politiche2022": {"cdx_votes": 162.0, "cdx_pct": 31.76470588235294, "csxm5s_votes": 344.0, "csxm5s_pct": 67.45098039215686, "total_votes": 510.0, "turnout": 51.724137931034484}}, {"section": 87, "politiche2022": {"cdx_votes": 59.0, "cdx_pct": 27.96208530805687, "csxm5s_votes": 148.0, "csxm5s_pct": 70.14218009478674, "total_votes": 211.0, "turnout": 38.29401088929219}}, {"section": 88, "politiche2022": {"cdx_votes": 107.0, "cdx_pct": 31.94029850746269, "csxm5s_votes": 221.0, "csxm5s_pct": 65.97014925373135, "total_votes": 335.0, "turnout": 44.906166219839136}}, {"section": 89, "politiche2022": {"cdx_votes": 139.0, "cdx_pct": 30.54945054945055, "csxm5s_votes": 307.0, "csxm5s_pct": 67.47252747252747, "total_votes": 455.0, "turnout": 53.655660377358494}}, {"section": 90, "politiche2022": {"cdx_votes": 179.0, "cdx_pct": 40.044742729306485, "csxm5s_votes": 257.0, "csxm5s_pct": 57.494407158836694, "total_votes": 447.0, "turnout": 50.45146726862303}}, {"section": 91, "politiche2022": {"cdx_votes": 151.0, "cdx_pct": 34.71264367816092, "csxm5s_votes": 266.0, "csxm5s_pct": 61.149425287356316, "total_votes": 435.0, "turnout": 51.17647058823529}}, {"section": 92, "politiche2022": {"cdx_votes": 138.0, "cdx_pct": 32.93556085918855, "csxm5s_votes": 258.0, "csxm5s_pct": 61.575178997613364, "total_votes": 419.0, "turnout": 49.06323185011709}}, {"section": 93, "politiche2022": {"cdx_votes": 139.0, "cdx_pct": 36.96808510638298, "csxm5s_votes": 220.0, "csxm5s_pct": 58.51063829787234, "total_votes": 376.0, "turnout": 50.673854447439346}}, {"section": 94, "politiche2022": {"cdx_votes": 141.0, "cdx_pct": 35.16209476309227, "csxm5s_votes": 247.0, "csxm5s_pct": 61.59600997506235, "total_votes": 401.0, "turnout": 44.11441144114411}}, {"section": 95, "politiche2022": {"cdx_votes": 76.0, "cdx_pct": 28.044280442804425, "csxm5s_votes": 183.0, "csxm5s_pct": 67.52767527675276, "total_votes": 271.0, "turnout": 43.29073482428115}}, {"section": 96, "politiche2022": {"cdx_votes": 92.0, "cdx_pct": 30.76923076923077, "csxm5s_votes": 198.0, "csxm5s_pct": 66.22073578595318, "total_votes": 299.0, "turnout": 45.64885496183206}}, {"section": 97, "politiche2022": {"cdx_votes": 121.0, "cdx_pct": 42.01388888888889, "csxm5s_votes": 153.0, "csxm5s_pct": 53.125, "total_votes": 288.0, "turnout": 48.8135593220339}}, {"section": 98, "politiche2022": {"cdx_votes": 170.0, "cdx_pct": 35.196687370600415, "csxm5s_votes": 291.0, "csxm5s_pct": 60.24844720496895, "total_votes": 483.0, "turnout": 47.39941118743866}}, {"section": 99, "politiche2022": {"cdx_votes": 195.0, "cdx_pct": 42.2077922077922, "csxm5s_votes": 252.0, "csxm5s_pct": 54.54545454545454, "total_votes": 462.0, "turnout": 50.38167938931297}}, {"section": 100, "politiche2022": {"cdx_votes": 136.0, "cdx_pct": 35.41666666666667, "csxm5s_votes": 231.0, "csxm5s_pct": 60.15625, "total_votes": 384.0, "turnout": 49.42084942084942}}, {"section": 101, "politiche2022": {"cdx_votes": 102.0, "cdx_pct": 30.815709969788518, "csxm5s_votes": 226.0, "csxm5s_pct": 68.27794561933534, "total_votes": 331.0, "turnout": 45.78146611341632}}, {"section": 102, "politiche2022": {"cdx_votes": 111.0, "cdx_pct": 35.57692307692308, "csxm5s_votes": 186.0, "csxm5s_pct": 59.61538461538461, "total_votes": 312.0, "turnout": 36.74911660777385}}, {"section": 103, "politiche2022": {"cdx_votes": 89.0, "cdx_pct": 29.96632996632997, "csxm5s_votes": 198.0, "csxm5s_pct": 66.66666666666666, "total_votes": 297.0, "turnout": 43.61233480176211}}, {"section": 104, "politiche2022": {"cdx_votes": 108.0, "cdx_pct": 31.213872832369944, "csxm5s_votes": 230.0, "csxm5s_pct": 66.47398843930635, "total_votes": 346.0, "turnout": 44.87678339818418}}, {"section": 105, "politiche2022": {"cdx_votes": 190.0, "cdx_pct": 39.66597077244259, "csxm5s_votes": 270.0, "csxm5s_pct": 56.36743215031316, "total_votes": 479.0, "turnout": 59.80024968789014}}, {"section": 106, "politiche2022": {"cdx_votes": 135.0, "cdx_pct": 33.088235294117645, "csxm5s_votes": 259.0, "csxm5s_pct": 63.48039215686274, "total_votes": 408.0, "turnout": 54.61847389558233}}, {"section": 107, "politiche2022": {"cdx_votes": 161.0, "cdx_pct": 37.704918032786885, "csxm5s_votes": 248.0, "csxm5s_pct": 58.07962529274005, "total_votes": 427.0, "turnout": 55.382619974059665}}, {"section": 108, "politiche2022": {"cdx_votes": 127.0, "cdx_pct": 34.794520547945204, "csxm5s_votes": 219.0, "csxm5s_pct": 60.0, "total_votes": 365.0, "turnout": 48.472775564409034}}, {"section": 109, "politiche2022": {"cdx_votes": 141.0, "cdx_pct": 31.263858093126384, "csxm5s_votes": 300.0, "csxm5s_pct": 66.51884700665188, "total_votes": 451.0, "turnout": 56.72955974842767}}, {"section": 110, "politiche2022": {"cdx_votes": 143.0, "cdx_pct": 35.221674876847295, "csxm5s_votes": 246.0, "csxm5s_pct": 60.591133004926114, "total_votes": 406.0, "turnout": 50.560398505603985}}, {"section": 111, "politiche2022": {"cdx_votes": 154.0, "cdx_pct": 36.57957244655582, "csxm5s_votes": 253.0, "csxm5s_pct": 60.09501187648456, "total_votes": 421.0, "turnout": 52.75689223057645}}, {"section": 112, "politiche2022": {"cdx_votes": 167.0, "cdx_pct": 36.86534216335541, "csxm5s_votes": 259.0, "csxm5s_pct": 57.17439293598234, "total_votes": 453.0, "turnout": 59.92063492063492}}, {"section": 113, "politiche2022": {"cdx_votes": 156.0, "cdx_pct": 37.05463182897862, "csxm5s_votes": 252.0, "csxm5s_pct": 59.857482185273156, "total_votes": 421.0, "turnout": 57.35694822888283}}, {"section": 114, "politiche2022": {"cdx_votes": 139.0, "cdx_pct": 35.824742268041234, "csxm5s_votes": 234.0, "csxm5s_pct": 60.30927835051546, "total_votes": 388.0, "turnout": 53.37001375515818}}, {"section": 115, "politiche2022": {"cdx_votes": 165.0, "cdx_pct": 39.95157384987893, "csxm5s_votes": 233.0, "csxm5s_pct": 56.416464891041166, "total_votes": 413.0, "turnout": 53.70611183355006}}, {"section": 116, "politiche2022": {"cdx_votes": 107.0, "cdx_pct": 29.155313351498634, "csxm5s_votes": 245.0, "csxm5s_pct": 66.7574931880109, "total_votes": 367.0, "turnout": 51.69014084507042}}, {"section": 117, "politiche2022": {"cdx_votes": 155.0, "cdx_pct": 36.13053613053613, "csxm5s_votes": 255.0, "csxm5s_pct": 59.44055944055944, "total_votes": 429.0, "turnout": 53.49127182044888}}, {"section": 118, "politiche2022": {"cdx_votes": 145.0, "cdx_pct": 32.15077605321508, "csxm5s_votes": 289.0, "csxm5s_pct": 64.07982261640798, "total_votes": 451.0, "turnout": 52.01845444059977}}, {"section": 119, "politiche2022": {"cdx_votes": 66.0, "cdx_pct": 37.93103448275862, "csxm5s_votes": 99.0, "csxm5s_pct": 56.896551724137936, "total_votes": 174.0, "turnout": 47.411444141689365}}, {"section": 120, "politiche2022": {"cdx_votes": 125.0, "cdx_pct": 34.530386740331494, "csxm5s_votes": 221.0, "csxm5s_pct": 61.04972375690608, "total_votes": 362.0, "turnout": 49.862258953168045}}, {"section": 121, "politiche2022": {"cdx_votes": 162.0, "cdx_pct": 38.20754716981132, "csxm5s_votes": 248.0, "csxm5s_pct": 58.490566037735846, "total_votes": 424.0, "turnout": 49.76525821596244}}, {"section": 122, "politiche2022": {"cdx_votes": 154.0, "cdx_pct": 32.48945147679325, "csxm5s_votes": 295.0, "csxm5s_pct": 62.236286919831215, "total_votes": 474.0, "turnout": 57.10843373493976}}, {"section": 123, "politiche2022": {"cdx_votes": 148.0, "cdx_pct": 33.789954337899545, "csxm5s_votes": 283.0, "csxm5s_pct": 64.61187214611871, "total_votes": 438.0, "turnout": 60.58091286307054}}, {"section": 124, "politiche2022": {"cdx_votes": 178.0, "cdx_pct": 38.362068965517246, "csxm5s_votes": 264.0, "csxm5s_pct": 56.896551724137936, "total_votes": 464.0, "turnout": 60.18158236057069}}, {"section": 125, "politiche2022": {"cdx_votes": 147.0, "cdx_pct": 35.59322033898305, "csxm5s_votes": 253.0, "csxm5s_pct": 61.25907990314769, "total_votes": 413.0, "turnout": 52.08070617906684}}, {"section": 126, "politiche2022": {"cdx_votes": 139.0, "cdx_pct": 35.012594458438286, "csxm5s_votes": 249.0, "csxm5s_pct": 62.72040302267003, "total_votes": 397.0, "turnout": 54.309165526675784}}, {"section": 127, "politiche2022": {"cdx_votes": 195.0, "cdx_pct": 34.946236559139784, "csxm5s_votes": 350.0, "csxm5s_pct": 62.72401433691756, "total_votes": 558.0, "turnout": 59.11016949152542}}, {"section": 128, "politiche2022": {"cdx_votes": 200.0, "cdx_pct": 41.067761806981515, "csxm5s_votes": 278.0, "csxm5s_pct": 57.08418891170432, "total_votes": 487.0, "turnout": 57.633136094674555}}, {"section": 129, "politiche2022": {"cdx_votes": 159.0, "cdx_pct": 42.74193548387097, "csxm5s_votes": 203.0, "csxm5s_pct": 54.56989247311827, "total_votes": 372.0, "turnout": 58.58267716535433}}, {"section": 130, "politiche2022": {"cdx_votes": 107.0, "cdx_pct": 36.64383561643836, "csxm5s_votes": 177.0, "csxm5s_pct": 60.61643835616438, "total_votes": 292.0, "turnout": 52.42369838420108}}, {"section": 131, "politiche2022": {"cdx_votes": 167.0, "cdx_pct": 39.11007025761124, "csxm5s_votes": 245.0, "csxm5s_pct": 57.377049180327866, "total_votes": 427.0, "turnout": 59.80392156862745}}, {"section": 132, "politiche2022": {"cdx_votes": 211.0, "cdx_pct": 42.973523421588595, "csxm5s_votes": 272.0, "csxm5s_pct": 55.397148676171085, "total_votes": 491.0, "turnout": 60.17156862745098}}, {"section": 133, "politiche2022": {"cdx_votes": 165.0, "cdx_pct": 40.04854368932039, "csxm5s_votes": 224.0, "csxm5s_pct": 54.36893203883495, "total_votes": 412.0, "turnout": 59.883720930232556}}, {"section": 134, "politiche2022": {"cdx_votes": 214.0, "cdx_pct": 43.85245901639344, "csxm5s_votes": 257.0, "csxm5s_pct": 52.66393442622951, "total_votes": 488.0, "turnout": 58.724428399518644}}, {"section": 135, "politiche2022": {"cdx_votes": 167.0, "cdx_pct": 36.784140969163, "csxm5s_votes": 268.0, "csxm5s_pct": 59.03083700440529, "total_votes": 454.0, "turnout": 58.73221216041398}}, {"section": 136, "politiche2022": {"cdx_votes": 190.0, "cdx_pct": 41.394335511982575, "csxm5s_votes": 250.0, "csxm5s_pct": 54.46623093681917, "total_votes": 459.0, "turnout": 58.02781289506953}}, {"section": 137, "politiche2022": {"cdx_votes": 204.0, "cdx_pct": 43.12896405919662, "csxm5s_votes": 254.0, "csxm5s_pct": 53.69978858350951, "total_votes": 473.0, "turnout": 58.75776397515528}}, {"section": 138, "politiche2022": {"cdx_votes": 156.0, "cdx_pct": 40.94488188976378, "csxm5s_votes": 216.0, "csxm5s_pct": 56.69291338582677, "total_votes": 381.0, "turnout": 47.92452830188679}}, {"section": 139, "politiche2022": {"cdx_votes": 160.0, "cdx_pct": 38.55421686746988, "csxm5s_votes": 242.0, "csxm5s_pct": 58.31325301204819, "total_votes": 415.0, "turnout": 51.36138613861386}}, {"section": 140, "politiche2022": {"cdx_votes": 143.0, "cdx_pct": 37.43455497382199, "csxm5s_votes": 215.0, "csxm5s_pct": 56.282722513089, "total_votes": 382.0, "turnout": 48.724489795918366}}, {"section": 141, "politiche2022": {"cdx_votes": 135.0, "cdx_pct": 38.90489913544668, "csxm5s_votes": 198.0, "csxm5s_pct": 57.06051873198847, "total_votes": 347.0, "turnout": 48.94217207334274}}, {"section": 142, "politiche2022": {"cdx_votes": 119.0, "cdx_pct": 38.019169329073485, "csxm5s_votes": 183.0, "csxm5s_pct": 58.46645367412141, "total_votes": 313.0, "turnout": 43.89901823281907}}, {"section": 143, "politiche2022": {"cdx_votes": 160.0, "cdx_pct": 38.64734299516908, "csxm5s_votes": 244.0, "csxm5s_pct": 58.93719806763285, "total_votes": 414.0, "turnout": 53.07692307692308}}, {"section": 144, "politiche2022": {"cdx_votes": 75.0, "cdx_pct": 30.48780487804878, "csxm5s_votes": 167.0, "csxm5s_pct": 67.88617886178862, "total_votes": 246.0, "turnout": 41.6243654822335}}, {"section": 145, "politiche2022": {"cdx_votes": 124.0, "cdx_pct": 36.795252225519285, "csxm5s_votes": 198.0, "csxm5s_pct": 58.753709198813056, "total_votes": 337.0, "turnout": 49.1970802919708}}, {"section": 146, "politiche2022": {"cdx_votes": 85.0, "cdx_pct": 32.56704980842912, "csxm5s_votes": 166.0, "csxm5s_pct": 63.601532567049816, "total_votes": 261.0, "turnout": 43.86554621848739}}, {"section": 147, "politiche2022": {"cdx_votes": 168.0, "cdx_pct": 36.36363636363637, "csxm5s_votes": 279.0, "csxm5s_pct": 60.3896103896104, "total_votes": 462.0, "turnout": 58.853503184713375}}, {"section": 148, "politiche2022": {"cdx_votes": 141.0, "cdx_pct": 36.62337662337662, "csxm5s_votes": 230.0, "csxm5s_pct": 59.74025974025974, "total_votes": 385.0, "turnout": 48.672566371681405}}, {"section": 149, "politiche2022": {"cdx_votes": 112.0, "cdx_pct": 36.12903225806451, "csxm5s_votes": 184.0, "csxm5s_pct": 59.354838709677416, "total_votes": 310.0, "turnout": 42.93628808864266}}, {"section": 150, "politiche2022": {"cdx_votes": 81.0, "cdx_pct": 28.321678321678323, "csxm5s_votes": 197.0, "csxm5s_pct": 68.88111888111888, "total_votes": 286.0, "turnout": 38.96457765667575}}, {"section": 151, "politiche2022": {"cdx_votes": 63.0, "cdx_pct": 30.0, "csxm5s_votes": 139.0, "csxm5s_pct": 66.19047619047619, "total_votes": 210.0, "turnout": 44.0251572327044}}, {"section": 152, "politiche2022": {"cdx_votes": 85.0, "cdx_pct": 36.79653679653679, "csxm5s_votes": 142.0, "csxm5s_pct": 61.471861471861466, "total_votes": 231.0, "turnout": 46.3855421686747}}, {"section": 153, "politiche2022": {"cdx_votes": 109.0, "cdx_pct": 33.746130030959755, "csxm5s_votes": 199.0, "csxm5s_pct": 61.60990712074303, "total_votes": 323.0, "turnout": 56.173913043478265}}, {"section": 154, "politiche2022": {"cdx_votes": 108.0, "cdx_pct": 40.909090909090914, "csxm5s_votes": 152.0, "csxm5s_pct": 57.57575757575758, "total_votes": 264.0, "turnout": 48.97959183673469}}, {"section": 155, "politiche2022": {"cdx_votes": 63.0, "cdx_pct": 25.71428571428571, "csxm5s_votes": 176.0, "csxm5s_pct": 71.83673469387755, "total_votes": 245.0, "turnout": 38.95071542130365}}, {"section": 156, "politiche2022": {"cdx_votes": 56.0, "cdx_pct": 25.0, "csxm5s_votes": 165.0, "csxm5s_pct": 73.66071428571429, "total_votes": 224.0, "turnout": 31.46067415730337}}, {"section": 157, "politiche2022": {"cdx_votes": 54.0, "cdx_pct": 23.17596566523605, "csxm5s_votes": 169.0, "csxm5s_pct": 72.53218884120172, "total_votes": 233.0, "turnout": 31.44399460188934}}, {"section": 158, "politiche2022": {"cdx_votes": 104.0, "cdx_pct": 32.5, "csxm5s_votes": 199.0, "csxm5s_pct": 62.18749999999999, "total_votes": 320.0, "turnout": 45.91104734576757}}, {"section": 159, "politiche2022": {"cdx_votes": 87.0, "cdx_pct": 24.369747899159663, "csxm5s_votes": 260.0, "csxm5s_pct": 72.82913165266106, "total_votes": 357.0, "turnout": 48.43962008141113}}, {"section": 160, "politiche2022": {"cdx_votes": 97.0, "cdx_pct": 29.48328267477204, "csxm5s_votes": 227.0, "csxm5s_pct": 68.9969604863222, "total_votes": 329.0, "turnout": 35.4908306364617}}, {"section": 161, "politiche2022": {"cdx_votes": 131.0, "cdx_pct": 31.951219512195124, "csxm5s_votes": 275.0, "csxm5s_pct": 67.07317073170732, "total_votes": 410.0, "turnout": 40.67460317460317}}, {"section": 162, "politiche2022": {"cdx_votes": 86.0, "cdx_pct": 29.054054054054053, "csxm5s_votes": 200.0, "csxm5s_pct": 67.56756756756756, "total_votes": 296.0, "turnout": 37.51584283903675}}, {"section": 163, "politiche2022": {"cdx_votes": 82.0, "cdx_pct": 27.242524916943523, "csxm5s_votes": 212.0, "csxm5s_pct": 70.43189368770764, "total_votes": 301.0, "turnout": 40.24064171122994}}, {"section": 164, "politiche2022": {"cdx_votes": 37.0, "cdx_pct": 20.108695652173914, "csxm5s_votes": 141.0, "csxm5s_pct": 76.63043478260869, "total_votes": 184.0, "turnout": 26.24821683309558}}, {"section": 165, "politiche2022": {"cdx_votes": 87.0, "cdx_pct": 26.605504587155966, "csxm5s_votes": 231.0, "csxm5s_pct": 70.64220183486239, "total_votes": 327.0, "turnout": 44.48979591836735}}, {"section": 166, "politiche2022": {"cdx_votes": 89.0, "cdx_pct": 27.9874213836478, "csxm5s_votes": 220.0, "csxm5s_pct": 69.18238993710692, "total_votes": 318.0, "turnout": 38.54545454545454}}, {"section": 167, "politiche2022": {"cdx_votes": 91.0, "cdx_pct": 33.95522388059701, "csxm5s_votes": 172.0, "csxm5s_pct": 64.17910447761194, "total_votes": 268.0, "turnout": 43.1561996779388}}, {"section": 168, "politiche2022": {"cdx_votes": 118.0, "cdx_pct": 37.10691823899371, "csxm5s_votes": 187.0, "csxm5s_pct": 58.80503144654088, "total_votes": 318.0, "turnout": 36.5097588978186}}, {"section": 169, "politiche2022": {"cdx_votes": 108.0, "cdx_pct": 31.671554252199414, "csxm5s_votes": 225.0, "csxm5s_pct": 65.98240469208211, "total_votes": 341.0, "turnout": 41.94341943419434}}, {"section": 170, "politiche2022": {"cdx_votes": 86.0, "cdx_pct": 26.461538461538463, "csxm5s_votes": 236.0, "csxm5s_pct": 72.61538461538461, "total_votes": 325.0, "turnout": 41.88144329896907}}, {"section": 171, "politiche2022": {"cdx_votes": 78.0, "cdx_pct": 24.148606811145513, "csxm5s_votes": 236.0, "csxm5s_pct": 73.06501547987617, "total_votes": 323.0, "turnout": 44.00544959128065}}, {"section": 172, "politiche2022": {"cdx_votes": 65.0, "cdx_pct": 24.43609022556391, "csxm5s_votes": 192.0, "csxm5s_pct": 72.18045112781954, "total_votes": 266.0, "turnout": 40.67278287461773}}, {"section": 173, "politiche2022": {"cdx_votes": 91.0, "cdx_pct": 28.706624605678233, "csxm5s_votes": 210.0, "csxm5s_pct": 66.24605678233438, "total_votes": 317.0, "turnout": 36.989498249708284}}, {"section": 174, "politiche2022": {"cdx_votes": 124.0, "cdx_pct": 28.837209302325583, "csxm5s_votes": 295.0, "csxm5s_pct": 68.6046511627907, "total_votes": 430.0, "turnout": 38.32442067736185}}, {"section": 175, "politiche2022": {"cdx_votes": 138.0, "cdx_pct": 24.555160142348754, "csxm5s_votes": 404.0, "csxm5s_pct": 71.88612099644128, "total_votes": 562.0, "turnout": 47.38617200674536}}, {"section": 176, "politiche2022": {"cdx_votes": 273.0, "cdx_pct": 33.171324422843256, "csxm5s_votes": 508.0, "csxm5s_pct": 61.72539489671932, "total_votes": 823.0, "turnout": 48.38330393885949}}, {"section": 177, "politiche2022": {"cdx_votes": 145.0, "cdx_pct": 32.07964601769911, "csxm5s_votes": 295.0, "csxm5s_pct": 65.2654867256637, "total_votes": 452.0, "turnout": 38.20794590025359}}, {"section": 178, "politiche2022": {"cdx_votes": 79.0, "cdx_pct": 22.76657060518732, "csxm5s_votes": 257.0, "csxm5s_pct": 74.06340057636888, "total_votes": 347.0, "turnout": 32.79773156899811}}, {"section": 179, "politiche2022": {"cdx_votes": 186.0, "cdx_pct": 36.75889328063241, "csxm5s_votes": 302.0, "csxm5s_pct": 59.683794466403164, "total_votes": 506.0, "turnout": 47.37827715355805}}, {"section": 180, "politiche2022": {"cdx_votes": 98.0, "cdx_pct": 28.405797101449277, "csxm5s_votes": 231.0, "csxm5s_pct": 66.95652173913044, "total_votes": 345.0, "turnout": 45.21625163826999}}, {"section": 181, "politiche2022": {"cdx_votes": 88.0, "cdx_pct": 27.41433021806853, "csxm5s_votes": 218.0, "csxm5s_pct": 67.91277258566979, "total_votes": 321.0, "turnout": 43.261455525606465}}, {"section": 182, "politiche2022": {"cdx_votes": 109.0, "cdx_pct": 30.277777777777775, "csxm5s_votes": 240.0, "csxm5s_pct": 66.66666666666666, "total_votes": 360.0, "turnout": 43.0622009569378}}, {"section": 183, "politiche2022": {"cdx_votes": 154.0, "cdx_pct": 34.92063492063492, "csxm5s_votes": 277.0, "csxm5s_pct": 62.81179138321995, "total_votes": 441.0, "turnout": 48.62183020948181}}, {"section": 184, "politiche2022": {"cdx_votes": 111.0, "cdx_pct": 25.813953488372093, "csxm5s_votes": 296.0, "csxm5s_pct": 68.83720930232559, "total_votes": 430.0, "turnout": 36.16484440706476}}, {"section": 185, "politiche2022": {"cdx_votes": 68.0, "cdx_pct": 25.27881040892193, "csxm5s_votes": 193.0, "csxm5s_pct": 71.74721189591078, "total_votes": 269.0, "turnout": 36.10738255033557}}, {"section": 186, "politiche2022": {"cdx_votes": 53.0, "cdx_pct": 20.784313725490197, "csxm5s_votes": 200.0, "csxm5s_pct": 78.43137254901961, "total_votes": 255.0, "turnout": 33.508541392904064}}, {"section": 187, "politiche2022": {"cdx_votes": 113.0, "cdx_pct": 34.76923076923077, "csxm5s_votes": 193.0, "csxm5s_pct": 59.38461538461538, "total_votes": 325.0, "turnout": 54.89864864864865}}, {"section": 188, "politiche2022": {"cdx_votes": 222.0, "cdx_pct": 32.408759124087595, "csxm5s_votes": 438.0, "csxm5s_pct": 63.94160583941606, "total_votes": 685.0, "turnout": 57.854729729729726}}, {"section": 189, "politiche2022": {"cdx_votes": 190.0, "cdx_pct": 33.80782918149466, "csxm5s_votes": 339.0, "csxm5s_pct": 60.320284697508896, "total_votes": 562.0, "turnout": 58.057851239669425}}, {"section": 190, "politiche2022": {"cdx_votes": 22.0, "cdx_pct": 44.89795918367347, "csxm5s_votes": 27.0, "csxm5s_pct": 55.10204081632652, "total_votes": 49.0, "turnout": null}}, {"section": 191, "politiche2022": {"cdx_votes": 99.0, "cdx_pct": 55.3072625698324, "csxm5s_votes": 76.0, "csxm5s_pct": 42.45810055865922, "total_votes": 179.0, "turnout": null}}]}